arrowlang/__init__.py
arrowlang/__main__.py
arrowlang/leaves.py
arrowlang/parser.py
arrowlang/runner.py
py_arrow_lang-2020.6.18.dist-info/LICENSE.txt
py_arrow_lang-2020.6.18.dist-info/METADATA
py_arrow_lang-2020.6.18.dist-info/WHEEL
py_arrow_lang-2020.6.18.dist-info/entry_points.txt
py_arrow_lang-2020.6.18.dist-info/top_level.txt
py_arrow_lang-2020.6.18.dist-info/RECORD
