Metadata-Version: 2.1
Name: py-arrow-lang
Version: 2020.6.18
Summary: An implementation of Arrow (https://github.com/jacob-g/arrow-lang) in Python.
Home-page: https://github.com/Kenny2github/py-arrow-lang
Author: Kenny2github
Author-email: kenny2minecraft@gmail.com
License: MIT
Keywords: arrow language interpreter
Platform: UNKNOWN
Classifier: Development Status :: 3 - Alpha
Classifier: License :: OSI Approved :: MIT License
Classifier: Programming Language :: Python :: 3.7
Classifier: Topic :: Software Development :: Interpreters
